cotacaoDolarAgora/__init__.py
cotacaoDolarAgora/main.py
cotacaodolaragora-0.2.dist-info/METADATA
cotacaodolaragora-0.2.dist-info/WHEEL
cotacaodolaragora-0.2.dist-info/entry_points.txt
cotacaodolaragora-0.2.dist-info/top_level.txt
cotacaodolaragora-0.2.dist-info/RECORD
